awpy/__init__.py
awpy/cli.py
awpy/constants.py
awpy/converters.py
awpy/demo.py
awpy/nav.py
awpy/spawn.py
awpy/vector.py
awpy/visibility.py
awpy/data/__init__.py
awpy/data/map_data.py
awpy/data/utils.py
awpy/parsers/__init__.py
awpy/parsers/bomb.py
awpy/parsers/clock.py
awpy/parsers/events.py
awpy/parsers/grenades.py
awpy/parsers/rounds.py
awpy/parsers/ticks.py
awpy/parsers/utils.py
awpy/plot/__init__.py
awpy/plot/nav.py
awpy/plot/plot.py
awpy/plot/utils.py
awpy/stats/__init__.py
awpy/stats/adr.py
awpy/stats/kast.py
awpy/stats/rating.py
awpy-2.0.2.dist-info/METADATA
awpy-2.0.2.dist-info/WHEEL
awpy-2.0.2.dist-info/entry_points.txt
awpy-2.0.2.dist-info/licenses/LICENSE
awpy-2.0.2.dist-info/RECORD
