Metadata-Version: 2.4
Name: awpy
Version: 2.0.2
Summary: Counter-Strike 2 demo parsing, analysis and visualization
Project-URL: Homepage, https://awpycs.com
Project-URL: Repository, https://github.com/pnxenopoulos/awpy
Project-URL: Docs, https://awpy.readthedocs.io/en/latest/?badge=latest
Author-email: Peter Xenopoulos <pnxenopoulos@gmail.com>
License-File: LICENSE
Keywords: counter strike,counter strike 2,counter-strike,counter-strike 2,cs2,csgo,esports,sports-analytics
Classifier: Intended Audience :: Science/Research
Classifier: License :: OSI Approved :: MIT License
Classifier: Programming Language :: Python :: 3.10
Classifier: Programming Language :: Python :: 3.11
Classifier: Programming Language :: Python :: 3.12
Classifier: Programming Language :: Python :: 3.13
Classifier: Topic :: Games/Entertainment
Classifier: Topic :: Games/Entertainment :: First Person Shooters
Classifier: Topic :: Scientific/Engineering :: Information Analysis
Requires-Python: <3.14,>=3.11
Requires-Dist: click>=8.1.8
Requires-Dist: demoparser2>=0.38.0
Requires-Dist: loguru>=0.7.3
Requires-Dist: matplotlib>=3.10.0
Requires-Dist: networkx>=3.4.2
Requires-Dist: numpy>=2.0.0
Requires-Dist: pillow>=11.1.0
Requires-Dist: polars>=1.22.0
Requires-Dist: requests>=2.32.3
Requires-Dist: scipy>=1.15.0
Requires-Dist: tqdm>=4.67.1
